tybles/__init__.py
tybles/py.typed
tybles-0.3.2.dist-info/WHEEL
tybles-0.3.2.dist-info/METADATA
tybles-0.3.2.dist-info/RECORD
