Metadata-Version: 2.1
Name: tybles
Version: 0.3.2
Summary: Tybles: simple schemas for Pandas dataframes
Home-page: https://github.com/denisrosset/tybles.git
License: BSD-3-Clause
Author: Denis Rosset
Author-email: physics@denisrosset.com
Requires-Python: >=3.8,<3.11
Classifier: License :: OSI Approved :: BSD License
Classifier: Programming Language :: Python :: 3
Classifier: Programming Language :: Python :: 3.10
Classifier: Programming Language :: Python :: 3.8
Classifier: Programming Language :: Python :: 3.9
Provides-Extra: beartype
Provides-Extra: docs
Provides-Extra: typeguard
Requires-Dist: beartype (>=0.10.4,<0.11.0); extra == "beartype"
Requires-Dist: ipykernel (>=6.13.0,<7.0.0); extra == "docs"
Requires-Dist: myst-nb (>=0.13.2,<0.14.0); extra == "docs"
Requires-Dist: numpy (>=1.22.3,<2.0.0)
Requires-Dist: pandas (>=1.2.4,<2.0.0)
Requires-Dist: pygments-csv-lexer (>=0.1.3,<0.2.0); extra == "docs"
Requires-Dist: sphinx (==4.3.2); extra == "docs"
Requires-Dist: sphinx-autodoc-typehints (>=1.17.0,<2.0.0); extra == "docs"
Requires-Dist: sphinx-book-theme (>=0.2.0,<0.3.0); extra == "docs"
Requires-Dist: typeguard (>=2.13.3,<3.0.0); extra == "typeguard"
Project-URL: Repository, https://github.com/denisrosset/tybles.git
